esteem/__init__.py
esteem/active_learning.py
esteem/drivers.py
esteem/parallel.py
esteem/trajectories.py
esteem/tasks/__init__.py
esteem/tasks/clusters.py
esteem/tasks/ml_debugger.py
esteem/tasks/ml_testing.py
esteem/tasks/ml_training.py
esteem/tasks/ml_trajectories.py
esteem/tasks/qmd_trajectories.py
esteem/tasks/solutes.py
esteem/tasks/solvate.py
esteem/tasks/spectra.py
esteem/wrappers/__init__.py
esteem/wrappers/amber.py
esteem/wrappers/amp.py
esteem/wrappers/ezfcf.py
esteem/wrappers/lammps.py
esteem/wrappers/mace.py
esteem/wrappers/nff.py
esteem/wrappers/nwchem.py
esteem/wrappers/onetep.py
esteem/wrappers/orca.py
esteem/wrappers/physnet.py
esteem/wrappers/specpycode.py
esteem-1.0.1.dist-info/LICENSE
esteem-1.0.1.dist-info/METADATA
esteem-1.0.1.dist-info/WHEEL
esteem-1.0.1.dist-info/top_level.txt
esteem-1.0.1.dist-info/RECORD
