Metadata-Version: 2.1
Name: esteem
Version: 1.0.1
Summary: Explicit Solvent Toolkit for Electronic Excitations of Molecules
Author-email: Nicholas Hine <n.d.m.hine@warwick.ac.uk>
Project-URL: Homepage, https://esteem.readthedocs.io/en/latest/
Project-URL: Bug Tracker, https://esteem.readthedocs.io/en/latest/
Classifier: Programming Language :: Python :: 3
Classifier: License :: OSI Approved :: MIT License
Classifier: Operating System :: OS Independent
Requires-Python: >=3.7
License-File: LICENSE
